registtro/__init__.py
registtro/_exceptions.py
registtro/_protocol.py
registtro/_registry.py
registtro/py.typed
registtro-1.4.0.dist-info/LICENSE
registtro-1.4.0.dist-info/METADATA
registtro-1.4.0.dist-info/WHEEL
registtro-1.4.0.dist-info/top_level.txt
registtro-1.4.0.dist-info/RECORD
